whoau/__init__.py
whoau/config.py
whoau/contents.py
whoau/dependency.py
whoau/display.py
whoau/localization.py
whoau/main.py
whoau/userid.py
whoau/utils.py
whoau-0.1.1.dist-info/LICENSE
whoau-0.1.1.dist-info/METADATA
whoau-0.1.1.dist-info/WHEEL
whoau-0.1.1.dist-info/entry_points.txt
whoau-0.1.1.dist-info/RECORD
