Metadata-Version: 2.1
Name: whoau
Version: 0.1.1
Summary: Have any questions? Take a moment to find out!
Home-page: https://github.com/dotpie/dotpie
License: MIT
Keywords: hello world,python,profile,readme
Author: dotpie
Author-email: mail@dotpie.dev
Maintainer: dotpie
Maintainer-email: mail@dotpie.dev
Requires-Python: >=3.8,<4.0
Classifier: License :: OSI Approved :: MIT License
Classifier: Programming Language :: Python :: 3
Classifier: Programming Language :: Python :: 3.8
Classifier: Programming Language :: Python :: 3.9
Classifier: Programming Language :: Python :: 3.10
Classifier: Programming Language :: Python :: 3.11
Classifier: Programming Language :: Python :: 3.12
Requires-Dist: requests (>=2.32.3,<3.0.0)
Requires-Dist: rich (>=13.7.1,<14.0.0)
Project-URL: Bug Tracker, https://github.com/dotpie/whoau/issues
Project-URL: Repository, https://github.com/dotpie/whoau
